LICENSE
gridthings/__init__.py
gridthings/cell.py
gridthings/collection.py
gridthings/grid.py
gridthings/typed_grids.py
gridthings-0.1.2.dist-info/LICENSE
gridthings-0.1.2.dist-info/WHEEL
gridthings-0.1.2.dist-info/METADATA
gridthings-0.1.2.dist-info/RECORD
